biosoundlab/__init__.py
biosoundlab/app.py
biosoundlab/models/__init__.py
biosoundlab/models/folder.py
biosoundlab/models/workspace.py
biosoundlab-0.1.0.dist-info/LICENSE
biosoundlab-0.1.0.dist-info/WHEEL
biosoundlab-0.1.0.dist-info/METADATA
biosoundlab-0.1.0.dist-info/RECORD
